setup.py
dbgap/__init__.py
dbgap/constants.py
dbgap/dbgap_study_information.py
dbgap/file_downloader.py
dbgap/json_to_rdf.py
dbgap/xform_dbgap.py
dbgap.egg-info/PKG-INFO
dbgap.egg-info/SOURCES.txt
dbgap.egg-info/dependency_links.txt
dbgap.egg-info/requires.txt
dbgap.egg-info/top_level.txt
scripts/download_study