Metadata-Version: 1.1
Name: dbgap
Version: 0.2.1
Summary: dbGaP to bioCaddie conversion utility
Home-page: http://github.com/crDDI/dbgap
Author: Harold Solbrig
Author-email: solbrig.harold@mayo.edu
License: BSD 3-Clause license
Platform: UNKNOWN
Classifier: Topic :: Software Development :: Libraries
Classifier: Programming Language :: Python :: 3
Classifier: Programming Language :: Python :: 3 :: Only
